chatllm/__init__.py
chatllm/chatllm.py
chatllm/qa.py
chatllm/utils.py
chatllm/applications/Question2Answer.py
chatllm/applications/__init__.py
chatllm/applications/ann4qa.py
chatllm/applications/chatbase.py
chatllm/applications/chatdoc.py
chatllm/applications/chatpdf.py
chatllm/applications/chatweb.py
chatllm/applications/crawler4qa.py
chatllm/applications/pipeline.py
chatllm/clis/README.md
chatllm/clis/__init__.py
chatllm/clis/cli.py
chatllm/kb/FaissANN.py
chatllm/kb/__init__.py
chatllm/kb/kbqa.py
chatllm/knowledge_base/__init__.py
chatllm/knowledge_base/lite.py
chatllm/parse_utils/__init__.py
chatllm/parse_utils/doc_embedding.py
chatllm/parse_utils/doc_parse.py
chatllm/textsplitter/__init__.py
chatllm/textsplitter/chinese_text_splitter.py
chatllm/uis/__init__.py
chatllm/uis/gradio_ui.py
ChatPDF-2023.4.25.9.25.56.dist-info/AUTHORS.rst
ChatPDF-2023.4.25.9.25.56.dist-info/LICENSE
ChatPDF-2023.4.25.9.25.56.dist-info/METADATA
ChatPDF-2023.4.25.9.25.56.dist-info/WHEEL
ChatPDF-2023.4.25.9.25.56.dist-info/entry_points.txt
ChatPDF-2023.4.25.9.25.56.dist-info/top_level.txt
ChatPDF-2023.4.25.9.25.56.dist-info/RECORD
